snowman/__init__.py
snowman/_cursor.py
snowman/_features.py
snowman/_generic.py
snowman/datatype.py
snowman/exception.py
snowman/py.typed
snowman/pydantic.py
snowman/query/__init__.py
snowman/query/builder/__init__.py
snowman/query/builder/_builder.py
snowman/query/builder/_delete_query_builder.py
snowman/query/builder/_insert_query_builder.py
snowman/query/builder/_select_query_builder.py
snowman/query/builder/_truncate_query_builder.py
snowman/query/builder/_update_query_builder.py
snowman/query/builder/condition/__init__.py
snowman/query/builder/condition/and_condition.py
snowman/query/builder/condition/condition.py
snowman/query/builder/condition/eq_condition.py
snowman/query/builder/condition/ge_condition.py
snowman/query/builder/condition/group_condition.py
snowman/query/builder/condition/gt_condition.py
snowman/query/builder/condition/in_condition.py
snowman/query/builder/condition/is_condition.py
snowman/query/builder/condition/is_not_condition.py
snowman/query/builder/condition/le_condition.py
snowman/query/builder/condition/lt_condition.py
snowman/query/builder/condition/ne_condition.py
snowman/query/builder/condition/not_in_condition.py
snowman/query/builder/condition/or_condition.py
snowman/query/builder/context/__init__.py
snowman/query/builder/context/order_by_context.py
snowman/query/builder/context/where_context.py
snowman/query/column.py
snowman/query/expression.py
snowman/query/minify.py
snowman/query/order_item.py
snowman/query/to_sql.py
snowman/relation/__init__.py
snowman/relation/table.py
snowman/relation/table_like.py
snowman/relation/view.py
snowman/typing.py
snowman_py-0.0.35.data/scripts/snowman.exe
snowman_py-0.0.35.dist-info/METADATA
snowman_py-0.0.35.dist-info/WHEEL
snowman_py-0.0.35.dist-info/RECORD
