Metadata-Version: 2.4
Name: snowman-py
Version: 0.0.35
Classifier: Programming Language :: Python :: Implementation :: CPython
Classifier: Programming Language :: Python :: Implementation :: PyPy
Classifier: Programming Language :: Rust
Requires-Dist: pydantic>=2.7.1
Requires-Dist: snowflake-connector-python>=3.10.1
Requires-Dist: typing-extensions>=4.12.0
Summary: Python model and query builder for Snowflake.
Author-email: ya7010 <ya7010@outlook.com>
Requires-Python: >=3.9
